{
  "dependencies":{
    "@feathersjs/configuration": "^4.5.12",
    "@feathersjs/errors": "^4.5.12",
    "@feathersjs/express": "^4.5.12",
    "@feathersjs/feathers": "^4.5.12",
    "@feathersjs/socketio": "^4.5.13",
    "@feathersjs/transport-commons": "^4.5.12",

    "@feathersjs/express": "^5.0.0-pre.38",
    "@feathersjs/feathers": "^5.0.0-pre.38",
    "@feathersjs/configuration": "^5.0.0-pre.38",
    "@feathersjs/koa": "^5.0.0-pre.38",
    "@feathersjs/transport-commons": "^5.0.0-pre.38",


    "@feathersjs_v4/configuration": "^4.5.12",
    "@feathersjs_v4/errors": "^4.5.12",
    "@feathersjs_v4/express": "^4.5.12",
    "@feathersjs_v4/feathers": "^4.5.12",
    "@feathersjs_v4/socketio": "^4.5.13",
    "@feathersjs_v4/transport-commons": "^4.5.12",

    "@feathersjs_v5/express": "npm:@feathersjs/express@^5.0.0-pre.38",
    "@feathersjs_v5/feathers": "npm:@feathersjs/feathers@^5.0.0-pre.38",
    "@feathersjs_v5/configuration": "npm:@feathersjs/configuration@^5.0.0-pre.38",
    "@feathersjs_v5/koa": "npm:@feathersjs/koa@^5.0.0-pre.38",
    "@feathersjs_v5/transport-commons": "npm:@feathersjs/transport-commons@^5.0.0-pre.38",
    "@feathersjs_v5/commons": "npm:@feathersjs/commons@^5.0.0-pre.38",

  },

  "overrides": {
    "@feathersjs/commons": "$@feathersjs_v5/commons",
    "@feathersjs/errors": "$@feathersjs_v5/errors",
    "@feathersjs/hooks": "$@feathersjs_v5/hooks",
    "@feathersjs/feathers": {
      ".": "$@feathersjs_v5/feathers",
      "@feathersjs/errors": "$@feathersjs_v5/errors",
      "@feathersjs/hooks": "$@feathersjs_v5/hooks",
      "@feathersjs/commons": "$@feathersjs_v5/commons"
    },
    "@feathersjs/express": {
      ".": "$@feathersjs_v5/express",
      "@feathersjs/feathers": "$@feathersjs_v5/feathers",
      "@feathersjs/errors": "$@feathersjs_v5/errors",
      "@feathersjs/hooks": "$@feathersjs_v5/hooks",
      "@feathersjs/commons": "$@feathersjs_v5/commons",
      "@feathersjs/authentication": "$@feathersjs_v5/authentication"
    },
    "@feathersjs/authentication": {
      ".": "$@feathersjs_v5/authentication",
      "@feathersjs/feathers": "$@feathersjs_v5/feathers",
      "@feathersjs/errors": "$@feathersjs_v5/errors",
      "@feathersjs/hooks": "$@feathersjs_v5/hooks",
      "@feathersjs/commons": "$@feathersjs_v5/commons",
      "@feathersjs/schema": "$@feathersjs_v5/schema"
    }
  }
}
